Workbook

Sheet Projeção
A1: Fluxo de caixa mensal — Out/26 a Mar/27
A2: Edite as linhas amarelas (vendas previstas). Custos vêm da aba Premissas.
B3: Out/26 | C3: Nov/26 | D3: Dez/26 | E3: Jan/27 | F3: Fev/27 | G3: Mar/27
A4: Mês nº | B4: 1 | C4: 2 | D4: 3 | E4: 4 | F4: 5 | G4: 6
A6: VENDAS
A7: Camisas vendidas (qtd) | B7: 73 | C7: 85 | D7: 100 | E7: 80 | F7: 90 | G7: 110
A8: Receita camisas | B8: =B7*Premissas!$B$7 -> 54312 | C8: =C7*Premissas!$B$7 -> 63240 | D8: =D7*Premissas!$B$7 -> 74400 | E8: =E7*Premissas!$B$7 -> 59520 | F8: =F7*Premissas!$B$7 -> 66960 | G8: =G7*Premissas!$B$7 -> 81840
A9: Receita alfaiataria (trajes, calças, ajustes) | B9: 20000 | C9: 20000 | D9: 20000 | E9: 20000 | F9: 20000 | G9: 20000
A10: Total de vendas | B10: =B8+B9 -> 74312 | C10: =C8+C9 -> 83240 | D10: =D8+D9 -> 94400 | E10: =E8+E9 -> 79520 | F10: =F8+F9 -> 86960 | G10: =G8+G9 -> 101840
A12: CUSTO DE PRODUÇÃO (vai para a conta 'Produção')
A13: Camisas: tecido + costura | B13: =B7*Premissas!$B$8 -> 19053 | C13: =C7*Premissas!$B$8 -> 22185 | D13: =D7*Premissas!$B$8 -> 26100 | E13: =E7*Premissas!$B$8 -> 20880 | F13: =F7*Premissas!$B$8 -> 23490 | G13: =G7*Premissas!$B$8 -> 28710
A14: Camisas: taxas e comissões | B14: =B7*Premissas!$B$9 -> 4343.5 | C14: =C7*Premissas!$B$9 -> 5057.5 | D14: =D7*Premissas!$B$9 -> 5950 | E14: =E7*Premissas!$B$9 -> 4760 | F14: =F7*Premissas!$B$9 -> 5355 | G14: =G7*Premissas!$B$9 -> 6545
A15: Alfaiataria: custo direto | B15: =B9*Premissas!$B$11 -> 7000 | C15: =C9*Premissas!$B$11 -> 7000 | D15: =D9*Premissas!$B$11 -> 7000 | E15: =E9*Premissas!$B$11 -> 7000 | F15: =F9*Premissas!$B$11 -> 7000 | G15: =G9*Premissas!$B$11 -> 7000
A16: Total custo de produção | B16: =SUM(B13:B15) -> 30396.5 | C16: =SUM(C13:C15) -> 34242.5 | D16: =SUM(D13:D15) -> 39050 | E16: =SUM(E13:E15) -> 32640 | F16: =SUM(F13:F15) -> 35845 | G16: =SUM(G13:G15) -> 42255
A18: CUSTOS FIXOS
A19: Aluguel ateliê | B19: =IF(B$4>=Premissas!$B$15,Premissas!$B$14,Premissas!$B$13) -> 1677.03 | C19: =IF(C$4>=Premissas!$B$15,Premissas!$B$14,Premissas!$B$13) -> 2400 | D19: =IF(D$4>=Premissas!$B$15,Premissas!$B$14,Premissas!$B$13) -> 2400 | E19: =IF(E$4>=Premissas!$B$15,Premissas!$B$14,Premissas!$B$13) -> 2400 | F19: =IF(F$4>=Premissas!$B$15,Premissas!$B$14,Premissas!$B$13) -> 2400 | G19: =IF(G$4>=Premissas!$B$15,Premissas!$B$14,Premissas!$B$13) -> 2400
A20: Multi Locações | B20: =Premissas!$B$16 -> 3674.63 | C20: =Premissas!$B$16 -> 3674.63 | D20: =Premissas!$B$16 -> 3674.63 | E20: =Premissas!$B$16 -> 3674.63 | F20: =Premissas!$B$16 -> 3674.63 | G20: =Premissas!$B$16 -> 3674.63
A21: Equipe fixa | B21: =Premissas!$B$17 -> 7000 | C21: =Premissas!$B$17 -> 7000 | D21: =Premissas!$B$17 -> 7000 | E21: =Premissas!$B$17 -> 7000 | F21: =Premissas!$B$17 -> 7000 | G21: =Premissas!$B$17 -> 7000
A22: Luz, telefone, internet | B22: =Premissas!$B$18 -> 632.68 | C22: =Premissas!$B$18 -> 632.68 | D22: =Premissas!$B$18 -> 632.68 | E22: =Premissas!$B$18 -> 632.68 | F22: =Premissas!$B$18 -> 632.68 | G22: =Premissas!$B$18 -> 632.68
A23: Plano de saúde | B23: =Premissas!$B$19 -> 573.22 | C23: =Premissas!$B$19 -> 573.22 | D23: =Premissas!$B$19 -> 573.22 | E23: =Premissas!$B$19 -> 573.22 | F23: =Premissas!$B$19 -> 573.22 | G23: =Premissas!$B$19 -> 573.22
A24: Contador | B24: =Premissas!$B$20 -> 400 | C24: =Premissas!$B$20 -> 400 | D24: =Premissas!$B$20 -> 400 | E24: =Premissas!$B$20 -> 400 | F24: =Premissas!$B$20 -> 400 | G24: =Premissas!$B$20 -> 400
A25: Sistemas | B25: =Premissas!$B$21 -> 698 | C25: =Premissas!$B$21 -> 698 | D25: =Premissas!$B$21 -> 698 | E25: =Premissas!$B$21 -> 698 | F25: =Premissas!$B$21 -> 698 | G25: =Premissas!$B$21 -> 698
A26: Impostos (DAS) | B26: =Premissas!$B$22 -> 800 | C26: =Premissas!$B$22 -> 800 | D26: =Premissas!$B$22 -> 800 | E26: =Premissas!$B$22 -> 800 | F26: =Premissas!$B$22 -> 800 | G26: =Premissas!$B$22 -> 800
A27: Transporte / estacionamento | B27: =Premissas!$B$23 -> 1400 | C27: =Premissas!$B$23 -> 1400 | D27: =Premissas!$B$23 -> 1400 | E27: =Premissas!$B$23 -> 1400 | F27: =Premissas!$B$23 -> 1400 | G27: =Premissas!$B$23 -> 1400
A28: Marketing | B28: =Premissas!$B$24 -> 1050 | C28: =Premissas!$B$24 -> 1050 | D28: =Premissas!$B$24 -> 1050 | E28: =Premissas!$B$24 -> 1050 | F28: =Premissas!$B$24 -> 1050 | G28: =Premissas!$B$24 -> 1050
A29: Total custos fixos | B29: =SUM(B19:B28) -> 17905.56 | C29: =SUM(C19:C28) -> 18628.53 | D29: =SUM(D19:D28) -> 18628.53 | E29: =SUM(E19:E28) -> 18628.53 | F29: =SUM(F19:F28) -> 18628.53 | G29: =SUM(G19:G28) -> 18628.53
A31: SOBRA DA OPERAÇÃO | B31: =B10-B16-B29 -> 26009.94 | C31: =C10-C16-C29 -> 30368.97 | D31: =D10-D16-D29 -> 36721.47 | E31: =E10-E16-E29 -> 28251.47 | F31: =F10-F16-F29 -> 32486.47 | G31: =G10-G16-G29 -> 40956.47
A33: VOCÊ, DÍVIDAS E INVESTIMENTO
A34: Retirada fixa (dias 5 e 20) | B34: =Premissas!$B$26 -> 20000 | C34: =Premissas!$B$26 -> 20000 | D34: =Premissas!$B$26 -> 20000 | E34: =Premissas!$B$26 -> 20000 | F34: =Premissas!$B$26 -> 20000 | G34: =Premissas!$B$26 -> 20000
A35: Empréstimo | B35: =IF(B$4=1,Premissas!$B$27,0) -> 2400 | C35: =IF(C$4=1,Premissas!$B$27,0) -> 0 | D35: =IF(D$4=1,Premissas!$B$27,0) -> 0 | E35: =IF(E$4=1,Premissas!$B$27,0) -> 0 | F35: =IF(F$4=1,Premissas!$B$27,0) -> 0 | G35: =IF(G$4=1,Premissas!$B$27,0) -> 0
A36: Máquinas / mudança | B36: =IF(AND(B$4>=Premissas!$B$31,B$4<Premissas!$B$31+Premissas!$B$30),Premissas!$B$29/Premissas!$B$30,0) -> 2500 | C36: =IF(AND(C$4>=Premissas!$B$31,C$4<Premissas!$B$31+Premissas!$B$30),Premissas!$B$29/Premissas!$B$30,0) -> 2500 | D36: =IF(AND(D$4>=Premissas!$B$31,D$4<Premissas!$B$31+Premissas!$B$30),Premissas!$B$29/Premissas!$B$30,0) -> 2500 | E36: =IF(AND(E$4>=Premissas!$B$31,E$4<Premissas!$B$31+Premissas!$B$30),Premissas!$B$29/Premissas!$B$30,0) -> 2500 | F36: =IF(AND(F$4>=Premissas!$B$31,F$4<Premissas!$B$31+Premissas!$B$30),Premissas!$B$29/Premissas!$B$30,0) -> 2500 | G36: =IF(AND(G$4>=Premissas!$B$31,G$4<Premissas!$B$31+Premissas!$B$30),Premissas!$B$29/Premissas!$B$30,0) -> 2500
A37: Total | B37: =SUM(B34:B36) -> 24900 | C37: =SUM(C34:C36) -> 22500 | D37: =SUM(D34:D36) -> 22500 | E37: =SUM(E34:E36) -> 22500 | F37: =SUM(F34:F36) -> 22500 | G37: =SUM(G34:G36) -> 22500
A39: RESULTADO DO MÊS | B39: =B31-B37 -> 1109.94 | C39: =C31-C37 -> 7868.97 | D39: =D31-D37 -> 14221.47 | E39: =E31-E37 -> 5751.47 | F39: =F31-F37 -> 9986.47 | G39: =G31-G37 -> 18456.47
A40: Saldo inicial | B40: =Premissas!$B$5 -> 9709.81 | C40: =B41 -> 10819.75 | D40: =C41 -> 18688.72 | E40: =D41 -> 32910.19 | F40: =E41 -> 38661.66 | G40: =F41 -> 48648.13
A41: SALDO FINAL DO MÊS | B41: =B40+B39 -> 10819.75 | C41: =C40+C39 -> 18688.72 | D41: =D40+D39 -> 32910.19 | E41: =E40+E39 -> 38661.66 | F41: =F40+F39 -> 48648.13 | G41: =G40+G39 -> 67104.6
A43: Meta de reserva ((custo fixo + retirada) × meses) | B43: =(B29+B34)*Premissas!$B$33 -> 37905.56 | C43: =(C29+C34)*Premissas!$B$33 -> 38628.53 | D43: =(D29+D34)*Premissas!$B$33 -> 38628.53 | E43: =(E29+E34)*Premissas!$B$33 -> 38628.53 | F43: =(F29+F34)*Premissas!$B$33 -> 38628.53 | G43: =(G29+G34)*Premissas!$B$33 -> 38628.53
A44: % da meta atingida | B44: =IF(B43=0,0,B41/B43) -> 0.28543966 | C44: =IF(C43=0,0,C41/C43) -> 0.48380614 | D44: =IF(D43=0,0,D41/D43) -> 0.85196589 | E44: =IF(E43=0,0,E41/E43) -> 1.0008577 | F44: =IF(F43=0,0,F41/F43) -> 1.2593834 | G44: =IF(G43=0,0,G41/G43) -> 1.7371772
A45: Separar p/ conta Produção em cada venda (%) | B45: =IF(B10=0,0,B16/B10) -> 0.40903892 | C45: =IF(C10=0,0,C16/C10) -> 0.41137074 | D45: =IF(D10=0,0,D16/D10) -> 0.41366525 | E45: =IF(E10=0,0,E16/E10) -> 0.41046278 | F45: =IF(F10=0,0,F16/F10) -> 0.41220101 | G45: =IF(G10=0,0,G16/G10) -> 0.41491555
A46: Camisas p/ pagar o aumento do aluguel | B46: =(Premissas!$B$14-Premissas!$B$13)/(Premissas!$B$7-Premissas!$B$8-Premissas!$B$9) -> 1.7071311 | C46: =(Premissas!$B$14-Premissas!$B$13)/(Premissas!$B$7-Premissas!$B$8-Premissas!$B$9) -> 1.7071311 | D46: =(Premissas!$B$14-Premissas!$B$13)/(Premissas!$B$7-Premissas!$B$8-Premissas!$B$9) -> 1.7071311 | E46: =(Premissas!$B$14-Premissas!$B$13)/(Premissas!$B$7-Premissas!$B$8-Premissas!$B$9) -> 1.7071311 | F46: =(Premissas!$B$14-Premissas!$B$13)/(Premissas!$B$7-Premissas!$B$8-Premissas!$B$9) -> 1.7071311 | G46: =(Premissas!$B$14-Premissas!$B$13)/(Premissas!$B$7-Premissas!$B$8-Premissas!$B$9) -> 1.7071311

Sheet Regras
B1: As 4 regras de caixa da Schuck
A3: 1 | B3: Separar a produção: a cada venda recebida, transferir o % da linha 'Separar p/ conta Produção' (aba Projeção) para uma conta/reserva separada. Esse dinheiro só paga tecido, costura e taxas.
A5: 2 | B5: Retirada fixa: o valor da Premissas, pago em 2 datas (dia 5 e dia 20). Cartão pessoal sai de dentro dela. Nada de Pix avulso da conta PJ.
A7: 3 | B7: Parcela do empréstimo vira reserva: a partir de novembro, o que ia para o empréstimo fica guardado até bater a meta de 1 mês de custo fixo.
A9: 4 | B9: Investimento só com sobra: máquinas e mudança parceladas ou pagas com pré-venda de camisas. O que não for essencial para dobrar a produção espera a reserva.
A11: ★ | B11: Pré-venda: cada ~35 camisas extras vendidas pagam R$ 15 mil de máquinas. Cobrando 100% antecipado, o cliente financia a expansão.

Sheet Premissas
A1: Schuck Alfaiataria — Premissas do fluxo de caixa
A2: Células em amarelo com número azul são para você editar. Todo o resto é calculado.
A4: CAIXA
A5: Saldo inicial em 01/10/2026 | B5: 9709.81 | C5: Saldo do extrato BTG em 24/09. Troque pelo saldo real de 30/09.
A6: CAMISARIA
A7: Preço médio por camisa | B7: 744 | C7: Seu sistema: Set/26 = R$ 54.334,59 ÷ 73 camisas.
A8: Custo direto por camisa (tecido + costura) | B8: 261 | C8: Seu sistema: (Valor − Margem) ÷ 73 = R$ 261. Você confirmou que inclui a costura.
A9: Taxas/comissões por camisa | B9: 59.5 | C9: Seu sistema: (Margem − Líquido) ÷ 73 = R$ 59,50.
A10: ALFAIATARIA (trajes, calças, ajustes)
A11: Custo direto da alfaiataria (% da venda) | B11: 0.35 | C11: Estimativa conservadora — ajuste quando tiver o número do sistema.
A12: CUSTOS FIXOS MENSAIS
A13: Aluguel ateliê — atual | B13: 1677.03 | C13: Crédito Real, extrato set/26.
A14: Aluguel ateliê — novo | B14: 2400 | C14: Informado por você.
A15: Mês em que o aluguel novo começa (1=Out … 6=Mar) | B15: 2 | C15: Você ainda não sabe; deixei novembro.
A16: Multi Locações | B16: 3674.63 | C16: Extrato: paga todo dia 1º (jul, ago, set). Confirmar o que é.
A17: Equipe fixa (Ícaro R$1.000/sem + Jair R$750/sem) | B17: 7000 | C17: Extrato: pagamentos semanais. Costura por peça já está no custo da camisa.
A18: Luz, telefone, internet | B18: 632.68 | C18: Sistema, set/26.
A19: Plano de saúde | B19: 573.22 | C19: Unimed, set/26.
A20: Contador | B20: 400 | C20: Gerson Carvalho, set/26.
A21: Sistemas (MoldeMe etc.) | B21: 698 | C21: Sistema, set/26.
A22: Impostos (DAS) | B22: 800 | C22: Variou de R$ 147 a R$ 1.319 nos 3 meses; usei uma média conservadora.
A23: Transporte / estacionamento | B23: 1400 | C23: Uber, estacionamento, combustível — extrato set/26.
A24: Marketing | B24: 1050 | C24: Sistema, set/26.
A25: VOCÊ E DÍVIDAS
A26: Retirada fixa mensal (inclui cartão pessoal) | B26: 20000 | C26: Regra: pagar em 2 datas (dia 5 e 20). Nada de Pix avulso.
A27: Empréstimo — saldo restante (pago em outubro) | B27: 2400 | C27: Informado por você.
A28: EXPANSÃO DA CAMISARIA
A29: Valor total máquinas + instalação + mudança | B29: 15000 | C29: Sua projeção (pode ficar menor).
A30: Nº de parcelas (1 = à vista) | B30: 6 | C30: Troque para 1 e veja o cenário à vista.
A31: Mês do 1º pagamento (1=Out … 6=Mar) | B31: 1
A32: RESERVA
A33: Meta — meses de (custo fixo + retirada) guardados | B33: 1 | C33: 1 mês = aguentar um mês sem vender nada. Meta 2 = 2 meses.

Sheet Semanal
A1: Acompanhamento semanal — preencha toda segunda-feira
A2: Amarelo = você preenche com o extrato. Meta de camisas = meta do mês ÷ semanas do mês.
A4: Semana (seg) | B4: Mês nº | C4: Meta camisas | D4: Camisas vendidas | E4: Entradas (R$) | F4: Saídas (R$) | G4: Saldo no banco | H4: Separado p/ Produção | I4: Diferença vs meta camisas | J4: Observação
A5: 46293 | B5: 1 | C5: =INDEX(Projeção!$B$7:$G$7,B5)/COUNTIF($B$5:$B$18,B5) -> 14.6 | I5: =IF(D5="","",D5-C5)
A6: 46300 | B6: 1 | C6: =INDEX(Projeção!$B$7:$G$7,B6)/COUNTIF($B$5:$B$18,B6) -> 14.6 | I6: =IF(D6="","",D6-C6)
A7: 46307 | B7: 1 | C7: =INDEX(Projeção!$B$7:$G$7,B7)/COUNTIF($B$5:$B$18,B7) -> 14.6 | I7: =IF(D7="","",D7-C7)
A8: 46314 | B8: 1 | C8: =INDEX(Projeção!$B$7:$G$7,B8)/COUNTIF($B$5:$B$18,B8) -> 14.6 | I8: =IF(D8="","",D8-C8)
A9: 46321 | B9: 1 | C9: =INDEX(Projeção!$B$7:$G$7,B9)/COUNTIF($B$5:$B$18,B9) -> 14.6 | I9: =IF(D9="","",D9-C9)
A10: 46328 | B10: 2 | C10: =INDEX(Projeção!$B$7:$G$7,B10)/COUNTIF($B$5:$B$18,B10) -> 21.25 | I10: =IF(D10="","",D10-C10)
A11: 46335 | B11: 2 | C11: =INDEX(Projeção!$B$7:$G$7,B11)/COUNTIF($B$5:$B$18,B11) -> 21.25 | I11: =IF(D11="","",D11-C11)
A12: 46342 | B12: 2 | C12: =INDEX(Projeção!$B$7:$G$7,B12)/COUNTIF($B$5:$B$18,B12) -> 21.25 | I12: =IF(D12="","",D12-C12)
A13: 46349 | B13: 2 | C13: =INDEX(Projeção!$B$7:$G$7,B13)/COUNTIF($B$5:$B$18,B13) -> 21.25 | I13: =IF(D13="","",D13-C13)
A14: 46356 | B14: 3 | C14: =INDEX(Projeção!$B$7:$G$7,B14)/COUNTIF($B$5:$B$18,B14) -> 20 | I14: =IF(D14="","",D14-C14)
A15: 46363 | B15: 3 | C15: =INDEX(Projeção!$B$7:$G$7,B15)/COUNTIF($B$5:$B$18,B15) -> 20 | I15: =IF(D15="","",D15-C15)
A16: 46370 | B16: 3 | C16: =INDEX(Projeção!$B$7:$G$7,B16)/COUNTIF($B$5:$B$18,B16) -> 20 | I16: =IF(D16="","",D16-C16)
... A18: 46384 | B18: 3 | C18: =INDEX(Projeção!$B$7:$G$7,B18)/COUNTIF($B$5:$B$18,B18) -> 20 | I18: =IF(D18="","",D18-C18)
A20: Exemplo de preenchimento: semana 28/09 → Camisas 18 · Entradas 21.500 · Saídas 17.200 · Saldo 14.000 · Separado 7.500
